{
  "updated": "2026-2-6 12:57:10",
  "setu": [
    {
      "file": "43.html",
      "caption": ""
    },
    {
      "file": "42.html",
      "caption": ""
    },
    {
      "file": "41.html",
      "caption": ""
    },
    {
      "file": "40.html",
      "caption": ""
    },
    {
      "file": "39.html",
      "caption": ""
    },
    {
      "file": "38.html",
      "caption": ""
    },
    {
      "file": "37.html",
      "caption": ""
    },
    {
      "file": "36.html",
      "caption": ""
    },
    {
      "file": "35.html",
      "caption": ""
    },
    {
      "file": "34.html",
      "caption": ""
    },
    {
      "file": "33.html",
      "caption": ""
    },
    {
      "file": "32.html",
      "caption": ""
    },
    {
      "file": "31.html",
      "caption": ""
    },
    {
      "file": "30.html",
      "caption": ""
    },
    {
      "file": "29.html",
      "caption": "ビッチな淫姉さまぁ #1"
    },
    {
      "file": "28.html",
      "caption": ""
    },
    {
      "file": "27.html",
      "caption": ""
    },
    {
      "file": "26.html",
      "caption": ""
    },
    {
      "file": "25.html",
      "caption": ""
    },
    {
      "file": "24.html",
      "caption": ""
    },
    {
      "file": "23.html",
      "caption": ""
    },
    {
      "file": "22.html",
      "caption": ""
    },
    {
      "file": "21.html",
      "caption": ""
    },
    {
      "file": "20.html",
      "caption": ""
    },
    {
      "file": "19.html",
      "caption": ""
    },
    {
      "file": "18.html",
      "caption": ""
    },
    {
      "file": "17.html",
      "caption": ""
    },
    {
      "file": "16.html",
      "caption": ""
    },
    {
      "file": "15.html",
      "caption": ""
    },
    {
      "file": "14.html",
      "caption": ""
    },
    {
      "file": "13.html",
      "caption": ""
    },
    {
      "file": "12.html",
      "caption": ""
    },
    {
      "file": "10.html",
      "caption": ""
    },
    {
      "file": "9.html",
      "caption": ""
    },
    {
      "file": "8.html",
      "caption": ""
    },
    {
      "file": "7.html",
      "caption": ""
    },
    {
      "file": "6.html",
      "caption": ""
    },
    {
      "file": "5.html",
      "caption": ""
    },
    {
      "file": "4.html",
      "caption": ""
    },
    {
      "file": "3.html",
      "caption": ""
    },
    {
      "file": "2.html",
      "caption": ""
    },
    {
      "file": "1.html",
      "caption": ""
    },
    {
      "file": "tb11.html",
      "caption": ""
    }
  ],
  "zrsetu": [
    {
      "file": "198.html",
      "caption": "# Umeko_J - Lucy Cyberpunk Edgerunner"
    },
    {
      "file": "197.html",
      "caption": "# 葛生 - No.012 甜心糖果"
    },
    {
      "file": "196.html",
      "caption": "# 清水凪 - No.012 手提箱与灰色女仆"
    },
    {
      "file": "195.html",
      "caption": "# Pure Media Vol.249 yeha (예하) - Bad delivery guy and new wife"
    },
    {
      "file": "194.html",
      "caption": "# 日奈娇 - 空姐"
    },
    {
      "file": "193.html",
      "caption": "# 星之迟迟 - 2025年12月计划G_她只是我的妹妹"
    },
    {
      "file": "192.html",
      "caption": "# 皮皮奶 - 葬送的芙莉莲·菲伦"
    },
    {
      "file": "191.html",
      "caption": "# yeonyu - [ARTGRAVIA] VOL.713"
    },
    {
      "file": "190.html",
      "caption": "# 年年 – 空姐2"
    },
    {
      "file": "189.html",
      "caption": "# 小仓千代w - Marin"
    },
    {
      "file": "188.html",
      "caption": "# Pure Media Vol.269 Yeha (예하) - Visit Suspicious Hospital"
    },
    {
      "file": "187.html",
      "caption": "# 咬一口兔娘_2026年01月订阅作品『在丈夫身边』"
    },
    {
      "file": "186.html",
      "caption": "# 年年 - 夏日物语 & 夏日时光"
    },
    {
      "file": "185.html",
      "caption": "# Pure Media Vol.155 Yeha (예하)"
    },
    {
      "file": "184.html",
      "caption": "# 一小央泽 - 拆礼物"
    },
    {
      "file": "183.html",
      "caption": "# yuuhui玉汇 - 搜查令"
    },
    {
      "file": "182.html",
      "caption": "# 屿鱼 - No.067 能代同人舞娘"
    },
    {
      "file": "181.html",
      "caption": "# 姜仁卿 -  X-Mas"
    },
    {
      "file": "180.html",
      "caption": "# 桜井宁宁 - 2025年12月订阅"
    },
    {
      "file": "179.html",
      "caption": "# Hina - Pure Media Vol.245 Pure gradoll"
    },
    {
      "file": "178.html",
      "caption": "# Pure Media Vol.294 Hina (히나) - Secret Meeting"
    },
    {
      "file": "177.html",
      "caption": "# PoppaChan - Marisa"
    },
    {
      "file": "176.html",
      "caption": "# 霜月shimo - No.148_女仆图鉴_Shimo's_Maid_Collection"
    },
    {
      "file": "175.html",
      "caption": "# 屿鱼 - No.066 桐生桔梗"
    },
    {
      "file": "174.html",
      "caption": "# 日奈娇 - 上门家教"
    },
    {
      "file": "173.html",
      "caption": "# 慕慕Momo - Escapism ▪︎ 逃避現實"
    },
    {
      "file": "172.html",
      "caption": "# Pure Media Vol.176 Yeha(예하) - Special"
    },
    {
      "file": "171.html",
      "caption": "# 雪晴Astra - No.101 原神·八重神子"
    },
    {
      "file": "170.html",
      "caption": "# yuuhui玉汇 - 有料少女2  中华少女"
    },
    {
      "file": "169.html",
      "caption": "# 清水凪 - No.009 圣诞 日&夜"
    },
    {
      "file": "168.html",
      "caption": "# Pure Media Vol.234 Yeha (예하) - Karaoke Hentai CallGirl"
    },
    {
      "file": "167.html",
      "caption": "# [Pure Media] Vol.265 Yeha (예하) - Hungry bitch in the stairwell"
    },
    {
      "file": "166.html",
      "caption": "# 小羊不吃草花音葉子 - 夏天的记忆"
    },
    {
      "file": "165.html",
      "caption": "# けん研（けんけん）_FantiaDL写真集_推し型メイドロイドとしたいこと"
    },
    {
      "file": "164.html",
      "caption": "# 北乃芽子_アルベド & 洛璃_No.086_碧蓝航线·花园兔女郎"
    },
    {
      "file": "163.html",
      "caption": "# rioko凉凉子 - 圣诞麋鹿套装"
    },
    {
      "file": "162.html",
      "caption": "# Machi马吉 - No.019 Aglaea阿格莱雅 & No.020 白色兔子"
    },
    {
      "file": "161.html",
      "caption": "# 星之迟迟 - 八月计划G-生日套"
    },
    {
      "file": "160.html",
      "caption": "# 虞梅_Yuumeilyn Princess Zelda - The_Legend_of_Zelda"
    },
    {
      "file": "159.html",
      "caption": "# 咬一口兔娘_2025年12月月票特典『床上管家』"
    },
    {
      "file": "158.html",
      "caption": "# 咬一口兔娘_2025年12月订阅作品『魔法圣诞星』"
    },
    {
      "file": "157.html",
      "caption": "# Bangni邦尼 - 三点式女仆"
    },
    {
      "file": "156.html",
      "caption": "# 桜井宁宁 - 宁宝TD"
    },
    {
      "file": "155.html",
      "caption": "# 清水凪 - No.005 普拉娜"
    },
    {
      "file": "154.html",
      "caption": "# 神楽坂真冬 - 白猫公主 & 爆机少女喵小吉 - 实习护士"
    },
    {
      "file": "153.html",
      "caption": "# 水淼Aqua - Birthday Bunny"
    },
    {
      "file": "152.html",
      "caption": "# Bangni邦尼 - No.054 沈妙泳装"
    },
    {
      "file": "151.html",
      "caption": "# yuuhui玉汇 - 升舱服务2 援"
    },
    {
      "file": "150.html",
      "caption": "# 鹿初 - 教室"
    },
    {
      "file": "149.html",
      "caption": "# 北川瑶 - 神里绫华"
    },
    {
      "file": "148.html",
      "caption": "# 鱼子酱Fish - 双人古装"
    },
    {
      "file": "147.html",
      "caption": "# 迷之呆梨 - 你的健身搭子"
    },
    {
      "file": "146.html",
      "caption": "# 咬一口兔娘_25年12月订阅作品『小酌怡情』"
    },
    {
      "file": "145.html",
      "caption": "# 铃木美咲 - 想成为你的偶像（大耳狗瑶篇）"
    },
    {
      "file": "144.html",
      "caption": "# 蠢沫沫 - 银镜伊织"
    },
    {
      "file": "143.html",
      "caption": "# 蠢沫沫 - 健身环"
    },
    {
      "file": "142.html",
      "caption": "# 爆机少女喵小吉 - 永恒魅魔"
    },
    {
      "file": "141.html",
      "caption": "# yuuhui玉汇 - 女仆假日"
    },
    {
      "file": "140.html",
      "caption": "# Yeha - [Pure Media] Vol.260 Stick my tail in the hole"
    },
    {
      "file": "139.html",
      "caption": "# Tsubaki Album Black Corset FullSize"
    },
    {
      "file": "138.html",
      "caption": "# PoppaChan - Coco Kiryuu (Hololive)"
    },
    {
      "file": "137.html",
      "caption": "# PoppaChan - Artoria Pendragon (Fate)"
    },
    {
      "file": "136.html",
      "caption": "# rioko凉凉子 - 碧蓝航线 近江 & 浅间"
    },
    {
      "file": "135.html",
      "caption": "# 年年 - 兔女郎番外篇 & 布丁大法 - 小蛋糕"
    },
    {
      "file": "134.html",
      "caption": "# 鹿八岁baby - No.076 花想容"
    },
    {
      "file": "133.html",
      "caption": "# Pure_Media Vol_300"
    },
    {
      "file": "132.html",
      "caption": "# Bangni邦尼 - No.053 男友衬衫"
    },
    {
      "file": "131.html",
      "caption": "# Pure_Media Vol_305"
    },
    {
      "file": "130.html",
      "caption": "# 日奈娇 - 下班的OL"
    },
    {
      "file": "129.html",
      "caption": "# 日奈娇 - 合欢宗圣女 & 教师灰丝"
    },
    {
      "file": "128.html",
      "caption": "# 咬一口兔娘Yiko湿润兔 -『浮枕朝颜_梦见月瑞希』红昭愿"
    },
    {
      "file": "127.html",
      "caption": "# 咬一口兔娘Yiko湿润兔 - 泥醉姉"
    },
    {
      "file": "126.html",
      "caption": "# 抱走莫子aa - 情人节限定-情迷"
    },
    {
      "file": "125.html",
      "caption": "# 云溪溪 - 奶桃桃×奈汐酱nice 花眠"
    },
    {
      "file": "124.html",
      "caption": "# 霜月shimo - 喜多川海梦 My Dress-Up"
    },
    {
      "file": "123.html",
      "caption": "# 神沢永莉 - 就这样圈住我吧"
    },
    {
      "file": "122.html",
      "caption": "# 桜井宁宁 - 眼镜OL"
    },
    {
      "file": "121.html",
      "caption": "# 云溪溪 - 奶桃桃＆奈汐酱nice - 墨朱"
    },
    {
      "file": "120.html",
      "caption": "# 年年 - 护士长の秘密"
    },
    {
      "file": "119.html",
      "caption": "# 蜜汁猫裘 - 柴郡花嫁"
    },
    {
      "file": "118.html",
      "caption": "# ARTGRAVIA - VOL.370"
    },
    {
      "file": "117.html",
      "caption": "# 蠢沫沫 - 透明护士"
    },
    {
      "file": "116.html",
      "caption": "# 禅院熏 - 夏日熏"
    },
    {
      "file": "115.html",
      "caption": "# 蠢沫沫 - 沫沫真爱版 圣天使"
    },
    {
      "file": "114.html",
      "caption": "# 清水由乃 - 荷叶粽"
    },
    {
      "file": "113.html",
      "caption": "# 咬一口兔娘_25年11月月票特典 - 加班秘书"
    },
    {
      "file": "112.html",
      "caption": "# yuuhui玉汇 - 幻蝶"
    },
    {
      "file": "111.html",
      "caption": "# 桜井宁宁 – 2025年11月会员订阅"
    },
    {
      "file": "110.html",
      "caption": "# 眼酱大魔王w - 热风"
    },
    {
      "file": "109.html",
      "caption": "# 梨霜儿 - 粉色礼服"
    },
    {
      "file": "108.html",
      "caption": "# けん研（けんけん）_FantiaDL写真集_KURO_Animals"
    },
    {
      "file": "107.html",
      "caption": "# 桜井宁宁 - 25年10月会员订阅系列"
    },
    {
      "file": "106.html",
      "caption": "# Yiko湿润兔 – 12月辐射_灰烬余生"
    },
    {
      "file": "105.html",
      "caption": "#PuyPuy_Chan - FGO：阿比盖尔 Abigail"
    },
    {
      "file": "104.html",
      "caption": "# Pure Media_Bada 이바다 - My Girl Friend"
    },
    {
      "file": "103.html",
      "caption": "# 星之迟迟_2025年06月计划G_热心的邻居姐姐"
    },
    {
      "file": "102.html",
      "caption": "# Yiko湿润兔 – 25年11月订阅作品『公主小妹』"
    },
    {
      "file": "101.html",
      "caption": "# 可可小白兔 - 意乱情迷の温泉之旅"
    },
    {
      "file": "100.html",
      "caption": "# neko酱 - 可爱乖巧学妹"
    },
    {
      "file": "99.html",
      "caption": "# 鱼子酱Fish - &杏子 最新双人演绎"
    },
    {
      "file": "98.html",
      "caption": "# 咬一口兔娘Yiko湿润兔 - 田舍生活"
    },
    {
      "file": "97.html",
      "caption": "# yuuhui玉汇 - 午夜治疗"
    },
    {
      "file": "96.html",
      "caption": "# 布丁大法 - [Perohub]25年05月订阅"
    },
    {
      "file": "95.html",
      "caption": "# 李佳 - 户外皮衣"
    },
    {
      "file": "94.html",
      "caption": "# 桜井宁宁 - 白丝修女"
    },
    {
      "file": "93.html",
      "caption": "# Pure_Media_Hina_히나_Share_My_Girlfriend"
    },
    {
      "file": "92.html",
      "caption": "# Ahae & Rua – ArtGravia"
    },
    {
      "file": "91.html",
      "caption": "# Pure_Media_Jelly_젤리_Is_Watching_Ero_Animation"
    },
    {
      "file": "90.html",
      "caption": "# Hina (히나) - Bitxx Training Outdoors"
    },
    {
      "file": "89.html",
      "caption": "# 桜井宁宁 - 风纪委员"
    },
    {
      "file": "88.html",
      "caption": "# 面饼仙儿 - 白色旗袍"
    },
    {
      "file": "87.html",
      "caption": "# 布丁大法_Perohub25年09月订阅作品"
    },
    {
      "file": "86.html",
      "caption": "# 李研雨 - Yeon_Woo_연우_Slip"
    },
    {
      "file": "85.html",
      "caption": "# 布丁大法_Perohub25年06月订阅作品8套"
    },
    {
      "file": "84.html",
      "caption": "# Bangni邦尼 - 埃及公主"
    },
    {
      "file": "83.html",
      "caption": "# 李素英（쏘블리） - leeesovely_Secret_Pictorial_2025_March"
    },
    {
      "file": "82.html",
      "caption": "# 梨霜儿&金允希 - 蜘蛛侠"
    },
    {
      "file": "81.html",
      "caption": "# Machi&小丁 温泉双人篇"
    },
    {
      "file": "80.html",
      "caption": "# 蠢沫沫x桃良阿宅 - 莉可莉丝"
    },
    {
      "file": "79.html",
      "caption": "# 落落Raku - 同級生の秘密"
    },
    {
      "file": "78.html",
      "caption": "# 星之迟迟 - 八月计划G"
    },
    {
      "file": "77.html",
      "caption": "# 蠢沫沫 & 桃良阿宅 - 同桌的你"
    },
    {
      "file": "76.html",
      "caption": "# 梨霜儿 - 电竞少女"
    },
    {
      "file": "75.html",
      "caption": "# Inkyung (강인경) - Girlfriend"
    },
    {
      "file": "74.html",
      "caption": "# Bangni邦尼 - 油润恶魔"
    },
    {
      "file": "73.html",
      "caption": "# yuuhui玉汇 - 粉兔束缚"
    },
    {
      "file": "72.html",
      "caption": "# 孙乐乐- Pure Media Vol.127"
    },
    {
      "file": "71.html",
      "caption": "# 神楽坂真冬 - 白丝兔绒"
    },
    {
      "file": "70.html",
      "caption": "# Janpan HDV"
    },
    {
      "file": "69.html",
      "caption": "# Tunlita - Vietnamese model"
    },
    {
      "file": "68.html",
      "caption": "# JVID-阿黎 - 光明黑暗吞噬塔罗少女"
    },
    {
      "file": "67.html",
      "caption": "# 桜井宁宁 - 失眠冲剂 搬运工"
    },
    {
      "file": "66.html",
      "caption": "# Vinnegal - Zelda"
    },
    {
      "file": "65.html",
      "caption": "# 清妙 - 湿身戏水"
    },
    {
      "file": "64.html",
      "caption": "# yuuhui玉汇 - 末影人"
    },
    {
      "file": "63.html",
      "caption": "# 年年 - 霓裳"
    },
    {
      "file": "62.html",
      "caption": "# 桜井宁宁 - 纯白花嫁"
    },
    {
      "file": "61.html",
      "caption": "# 布丁大法 - 万圣节 幽灵小姐"
    },
    {
      "file": "60.html",
      "caption": "# 肉包Mini - 沈迷色色の可愛女友"
    },
    {
      "file": "59.html",
      "caption": "# 有喵酱 - 白の絲"
    },
    {
      "file": "58.html",
      "caption": "# 桜井宁宁 - 关于我家可爱的女仆"
    },
    {
      "file": "57.html",
      "caption": "# PoppaChan - 卡提希娅Cartethyia"
    },
    {
      "file": "56.html",
      "caption": "# Bangni邦尼 - 灰色毛衣"
    },
    {
      "file": "55.html",
      "caption": "# 高桥千凛 - 蓝莓果酱"
    },
    {
      "file": "54.html",
      "caption": "# 呆呆Misa - 卡提希娅"
    },
    {
      "file": "53.html",
      "caption": "# Serena"
    },
    {
      "file": "52.html",
      "caption": "# yuuhui玉汇 - 柳如烟"
    },
    {
      "file": "51.html",
      "caption": "# 奈汐酱nice - 金笺寄月"
    },
    {
      "file": "50.html",
      "caption": "# 六味帝皇酱 - 幼稚园随拍"
    },
    {
      "file": "49.html",
      "caption": "# #慕慕Momo - 纳西妲"
    },
    {
      "file": "48.html",
      "caption": "# 布丁大法 - 白发女友"
    },
    {
      "file": "47.html",
      "caption": "# 六味帝皇酱 - 五一假日女友"
    },
    {
      "file": "46.html",
      "caption": "# 浅安安 - 浴"
    },
    {
      "file": "45.html",
      "caption": "# 六味帝皇酱 - 午后的少女"
    },
    {
      "file": "44.html",
      "caption": "# 六味帝皇酱 - 小艺LOX洛丽塔"
    },
    {
      "file": "43.html",
      "caption": "# 六味帝皇酱 - 厕所JK"
    },
    {
      "file": "42.html",
      "caption": "# 梨霜儿 - 黑胶唱片"
    },
    {
      "file": "41.html",
      "caption": "# 日奈娇 - 前妻"
    },
    {
      "file": "40.html",
      "caption": "# LEEHEE EXPRESS LERB-093 Na Kyung"
    },
    {
      "file": "39.html",
      "caption": "# 鱼子酱Fish – 双人睡裙女仆"
    },
    {
      "file": "38.html",
      "caption": "# yuuhui玉汇 – 柳如烟"
    },
    {
      "file": "37.html",
      "caption": "# 疯猫ss – 亲爱的520 符箓你"
    },
    {
      "file": "36.html",
      "caption": "# 杏子Yada - 天台"
    },
    {
      "file": "35.html",
      "caption": "# 迷之呆梨_Fantia25年08月会员订阅合集"
    },
    {
      "file": "34.html",
      "caption": "# 蠢沫沫 - 黄豆粉"
    },
    {
      "file": "33.html",
      "caption": ""
    },
    {
      "file": "32.html",
      "caption": ""
    },
    {
      "file": "31.html",
      "caption": "# 高桥千凛 - 油光连体黑丝"
    },
    {
      "file": "30.html",
      "caption": "# 梨霜儿 - 唐装"
    },
    {
      "file": "29.html",
      "caption": ""
    },
    {
      "file": "28.html",
      "caption": ""
    },
    {
      "file": "27.html",
      "caption": ""
    },
    {
      "file": "26.html",
      "caption": ""
    },
    {
      "file": "25.html",
      "caption": ""
    },
    {
      "file": "24.html",
      "caption": ""
    },
    {
      "file": "23.html",
      "caption": ""
    },
    {
      "file": "22.html",
      "caption": ""
    },
    {
      "file": "21.html",
      "caption": ""
    },
    {
      "file": "20.html",
      "caption": ""
    },
    {
      "file": "19.html",
      "caption": ""
    },
    {
      "file": "18.html",
      "caption": ""
    },
    {
      "file": "17.html",
      "caption": ""
    },
    {
      "file": "16.html",
      "caption": ""
    },
    {
      "file": "15.html",
      "caption": "# 年年 - 海上花"
    },
    {
      "file": "14.html",
      "caption": "# 小恩 -  捆绑"
    },
    {
      "file": "13.html",
      "caption": ""
    },
    {
      "file": "12.html",
      "caption": ""
    },
    {
      "file": "11.html",
      "caption": ""
    },
    {
      "file": "10.html",
      "caption": ""
    },
    {
      "file": "9.html",
      "caption": ""
    },
    {
      "file": "8.html",
      "caption": ""
    },
    {
      "file": "7.html",
      "caption": ""
    },
    {
      "file": "6.html",
      "caption": ""
    },
    {
      "file": "5.html",
      "caption": "# YeEun - Kimetsu no Yaiba Mitsuri Kanroji"
    },
    {
      "file": "4.html",
      "caption": "# yuuhui玉汇 - 水中花"
    },
    {
      "file": "3.html",
      "caption": "# 少女映画 - 友利奈绪"
    },
    {
      "file": "2.html",
      "caption": "# 少女映画 - Azuma Seren"
    },
    {
      "file": "1.html",
      "caption": "# 少女映画 - 丰川祥子 Togawa_Sakiko_BanG_Dream!"
    }
  ]
}