{
  "updated": "2026-7-14 20:37:12",
  "acg": [],
  "setu": [],
  "zrsetu": [
    {
      "file": "162.html",
      "caption": "# Machi马吉 - No.019 Aglaea阿格莱雅 & No.020 白色兔子"
    },
    {
      "file": "161.html",
      "caption": "# 星之迟迟 - 八月计划G-生日套"
    },
    {
      "file": "160.html",
      "caption": "# 虞梅_Yuumeilyn Princess Zelda - The_Legend_of_Zelda"
    },
    {
      "file": "159.html",
      "caption": "# 咬一口兔娘_2025年12月月票特典『床上管家』"
    },
    {
      "file": "158.html",
      "caption": "# 咬一口兔娘_2025年12月订阅作品『魔法圣诞星』"
    },
    {
      "file": "157.html",
      "caption": "# Bangni邦尼 - 三点式女仆"
    },
    {
      "file": "156.html",
      "caption": "# 桜井宁宁 - 宁宝TD"
    },
    {
      "file": "155.html",
      "caption": "# 清水凪 - No.005 普拉娜"
    },
    {
      "file": "154.html",
      "caption": "# 神楽坂真冬 - 白猫公主 & 爆机少女喵小吉 - 实习护士"
    },
    {
      "file": "153.html",
      "caption": "# 水淼Aqua - Birthday Bunny"
    },
    {
      "file": "152.html",
      "caption": "# Bangni邦尼 - No.054 沈妙泳装"
    },
    {
      "file": "151.html",
      "caption": "# yuuhui玉汇 - 升舱服务2 援"
    },
    {
      "file": "150.html",
      "caption": "# 鹿初 - 教室"
    },
    {
      "file": "149.html",
      "caption": "# 北川瑶 - 神里绫华"
    },
    {
      "file": "148.html",
      "caption": "# 鱼子酱Fish - 双人古装"
    },
    {
      "file": "147.html",
      "caption": "# 迷之呆梨 - 你的健身搭子"
    },
    {
      "file": "146.html",
      "caption": "# 咬一口兔娘_25年12月订阅作品『小酌怡情』"
    },
    {
      "file": "145.html",
      "caption": "# 铃木美咲 - 想成为你的偶像（大耳狗瑶篇）"
    },
    {
      "file": "144.html",
      "caption": "# 蠢沫沫 - 银镜伊织"
    },
    {
      "file": "143.html",
      "caption": "# 蠢沫沫 - 健身环"
    },
    {
      "file": "142.html",
      "caption": "# 爆机少女喵小吉 - 永恒魅魔"
    },
    {
      "file": "141.html",
      "caption": "# yuuhui玉汇 - 女仆假日"
    },
    {
      "file": "140.html",
      "caption": "# Yeha - [Pure Media] Vol.260 Stick my tail in the hole"
    },
    {
      "file": "139.html",
      "caption": "# Tsubaki Album Black Corset FullSize"
    },
    {
      "file": "138.html",
      "caption": "# PoppaChan - Coco Kiryuu (Hololive)"
    },
    {
      "file": "137.html",
      "caption": "# PoppaChan - Artoria Pendragon (Fate)"
    },
    {
      "file": "136.html",
      "caption": "# rioko凉凉子 - 碧蓝航线 近江 & 浅间"
    },
    {
      "file": "135.html",
      "caption": "# 年年 - 兔女郎番外篇 & 布丁大法 - 小蛋糕"
    },
    {
      "file": "134.html",
      "caption": "# 鹿八岁baby - No.076 花想容"
    },
    {
      "file": "133.html",
      "caption": "# Pure_Media Vol_300"
    },
    {
      "file": "132.html",
      "caption": "# Bangni邦尼 - No.053 男友衬衫"
    },
    {
      "file": "131.html",
      "caption": "# Pure_Media Vol_305"
    },
    {
      "file": "130.html",
      "caption": "# 日奈娇 - 下班的OL"
    },
    {
      "file": "129.html",
      "caption": "# 日奈娇 - 合欢宗圣女 & 教师灰丝"
    },
    {
      "file": "128.html",
      "caption": "# 咬一口兔娘Yiko湿润兔 -『浮枕朝颜_梦见月瑞希』红昭愿"
    },
    {
      "file": "127.html",
      "caption": "# 咬一口兔娘Yiko湿润兔 - 泥醉姉"
    },
    {
      "file": "126.html",
      "caption": "# 抱走莫子aa - 情人节限定-情迷"
    },
    {
      "file": "125.html",
      "caption": "# 云溪溪 - 奶桃桃×奈汐酱nice 花眠"
    },
    {
      "file": "124.html",
      "caption": "# 霜月shimo - 喜多川海梦 My Dress-Up"
    },
    {
      "file": "123.html",
      "caption": "# 神沢永莉 - 就这样圈住我吧"
    },
    {
      "file": "122.html",
      "caption": "# 桜井宁宁 - 眼镜OL"
    },
    {
      "file": "121.html",
      "caption": "# 云溪溪 - 奶桃桃＆奈汐酱nice - 墨朱"
    },
    {
      "file": "120.html",
      "caption": "# 年年 - 护士长の秘密"
    },
    {
      "file": "119.html",
      "caption": "# 蜜汁猫裘 - 柴郡花嫁"
    },
    {
      "file": "118.html",
      "caption": "# ARTGRAVIA - VOL.370"
    },
    {
      "file": "117.html",
      "caption": "# 蠢沫沫 - 透明护士"
    },
    {
      "file": "116.html",
      "caption": "# 禅院熏 - 夏日熏"
    },
    {
      "file": "115.html",
      "caption": "# 蠢沫沫 - 沫沫真爱版 圣天使"
    },
    {
      "file": "114.html",
      "caption": "# 清水由乃 - 荷叶粽"
    },
    {
      "file": "113.html",
      "caption": "# 咬一口兔娘_25年11月月票特典 - 加班秘书"
    }
  ]
}